citoolkit/__init__.py
citoolkit/improvisers/__init__.py
citoolkit/improvisers/classic_ci.py
citoolkit/improvisers/improviser.py
citoolkit/specifications/__init__.py
citoolkit/specifications/dfa.py
citoolkit/specifications/spec.py
citoolkit-0.1.0.dist-info/LICENSE
citoolkit-0.1.0.dist-info/WHEEL
citoolkit-0.1.0.dist-info/METADATA
citoolkit-0.1.0.dist-info/RECORD
